pandas_query_tool/__init__.py
pandas_query_tool/main.py
pandas_query_tool/internal/__init__.py
pandas_query_tool/internal/response.py
pandas_query_tool/libs/__init__.py
pandas_query_tool/libs/startHelper.py
pandas_query_tool/middlewares/__init__.py
pandas_query_tool/middlewares/apply.py
pandas_query_tool/middlewares/change_assets_path.py
pandas_query_tool/middlewares/change_content_type.py
pandas_query_tool/middlewares/defaultIndex.py
pandas_query_tool/models/__init__.py
pandas_query_tool/models/dataModel.py
pandas_query_tool/routers/__init__.py
pandas_query_tool/routers/methods.py
pandas_query_tool/static/__init__.py
pandas_query_tool/static/favicon.ico
pandas_query_tool/static/index.html
pandas_query_tool/static/assets/__init__.py
pandas_query_tool/static/assets/index.38064535.css
pandas_query_tool/static/assets/index.8dcd118e.js
pandas_query_tool/static/assets/vendor.85ddb413.js
pandas_query_tool-1.0.5.dist-info/METADATA
pandas_query_tool-1.0.5.dist-info/WHEEL
pandas_query_tool-1.0.5.dist-info/entry_points.txt
pandas_query_tool-1.0.5.dist-info/top_level.txt
pandas_query_tool-1.0.5.dist-info/RECORD
